src/__init__.py
src/backend_client.py
src/server.py
src/state.py
src/tools/__init__.py
src/tools/build.py
src/tools/build_old.py
src/tools/configure.py
src/tools/connect.py
src/tools/execute.py
src/tools/runsuite.py
src/tools/usage.py
mahoraga_mcp-0.2.0.dist-info/METADATA
mahoraga_mcp-0.2.0.dist-info/WHEEL
mahoraga_mcp-0.2.0.dist-info/entry_points.txt
mahoraga_mcp-0.2.0.dist-info/RECORD
