Metadata-Version: 2.4
Name: mahoraga-mcp
Version: 0.2.0
Summary: Model Context Protocol server for Mahoraga - AI-powered mobile automation agent
Project-URL: Homepage, https://mahoraga.app
Project-URL: Repository, https://github.com/mahoraga/mahoraga-mcp
Project-URL: Documentation, https://docs.mahoraga.app
Project-URL: Issues, https://github.com/mahoraga/mahoraga-mcp/issues
Author-email: Mahoraga Team <hello@mahoraga.app>
License: MIT
Keywords: ai,android,mahoraga,mcp,mobile-automation,testing
Classifier: Development Status :: 4 - Beta
Classifier: Intended Audience :: Developers
Classifier: License :: OSI Approved :: MIT License
Classifier: Programming Language :: Python :: 3.11
Classifier: Programming Language :: Python :: 3.12
Classifier: Programming Language :: Python :: 3.13
Classifier: Topic :: Software Development :: Testing
Requires-Python: >=3.11
Requires-Dist: adbutils==2.10.0
Requires-Dist: apkutils==2.0.0
Requires-Dist: click>=8.1.0
Requires-Dist: httpx>=0.27.0
Requires-Dist: mcp>=0.9.0
Requires-Dist: pydantic>=2.0.0
Requires-Dist: python-dotenv>=1.0.0
Requires-Dist: rich>=13.0.0
Provides-Extra: dev
Requires-Dist: pytest-asyncio>=0.21.0; extra == 'dev'
Requires-Dist: pytest>=7.0.0; extra == 'dev'
